redditpythonapi/__init__.py
redditpythonapi/reddit.py
reddit_python_api-0.12.dist-info/LICENSE
reddit_python_api-0.12.dist-info/METADATA
reddit_python_api-0.12.dist-info/WHEEL
reddit_python_api-0.12.dist-info/top_level.txt
reddit_python_api-0.12.dist-info/RECORD
