Metadata-Version: 2.1
Name: reddit-python-api
Version: 0.12
Summary: A simple Reddit Python API
Author-email: Electronic Mango <78230210+Electronic-Mango@users.noreply.github.com>
License: GNU GENERAL PUBLIC LICENSE
Project-URL: Homepage, https://github.com/Electronic-Mango/reddit-python-api
Project-URL: Documentation, https://electronic-mango.github.io/reddit-python-api
Project-URL: Repository, https://github.com/Electronic-Mango/reddit-python-api
Keywords: reddit,api
Classifier: Development Status :: 3 - Alpha
Classifier: Intended Audience :: Developers
Classifier: Topic :: Software Development :: Build Tools
Classifier: License :: OSI Approved :: GNU General Public License v3 (GPLv3)
Classifier: Programming Language :: Python :: 3
Classifier: Programming Language :: Python :: 3.11
Requires-Python: >=3.11
License-File: LICENSE
Requires-Dist: httpx
